Metadata-Version: 1.1
Name: sentianalyse
Version: 0.0.1
Summary: A small tool for sentiment analysis of texts.
Home-page: https://github.com/garain/sentianalyse
Author: Avishek Garain
Author-email: avishekgarain@gmail.com
License: MIT
Keywords: sentiment polarity emotion texts
Platform: UNKNOWN
Classifier: Development Status :: 3 - Alpha
Classifier: Intended Audience :: Developers
Classifier: Topic :: Internet
Classifier: License :: OSI Approved :: MIT License
Classifier: Programming Language :: Python
Classifier: Programming Language :: Python :: 2
Classifier: Programming Language :: Python :: 2.6
Classifier: Programming Language :: Python :: 2.7
Classifier: Programming Language :: Python :: 3
Classifier: Programming Language :: Python :: 3.3
Classifier: Programming Language :: Python :: 3.4
Classifier: Programming Language :: Python :: 3.5
